twomartens.markdown-1.0.0.dev4-py3.6-nspkg.pth
twomartens/markdown/__init__.py
twomartens/markdown/__main__.py
twomartens/markdown/grammars.py
twomartens/markdown/markdown.py
twomartens/markdown/parser.py
twomartens/markdown/renderer.py
twomartens/markdown/templates/skeleton.html
twomartens.markdown-1.0.0.dev4.dist-info/DESCRIPTION.rst
twomartens.markdown-1.0.0.dev4.dist-info/METADATA
twomartens.markdown-1.0.0.dev4.dist-info/RECORD
twomartens.markdown-1.0.0.dev4.dist-info/WHEEL
twomartens.markdown-1.0.0.dev4.dist-info/entry_points.txt
twomartens.markdown-1.0.0.dev4.dist-info/metadata.json
twomartens.markdown-1.0.0.dev4.dist-info/namespace_packages.txt
twomartens.markdown-1.0.0.dev4.dist-info/top_level.txt
