Metadata-Version: 2.0
Name: twomartens.markdown
Version: 1.0.0.dev4
Summary: Markdown parser that renders the markdown in HTML
Home-page: https://github.com/frmwrk123/markdown-parser
Author: Jim Martens
Author-email: github@2martens.de
License: Apache Software License
Platform: UNKNOWN
Classifier: Operating System :: OS Independent
Classifier: Development Status :: 2 - Pre-Alpha
Classifier: License :: OSI Approved :: Apache Software License
Classifier: Environment :: Console
Classifier: Topic :: Text Processing :: Markup
Classifier: Programming Language :: Python :: 3
Classifier: Programming Language :: Python :: 3.5
Classifier: Programming Language :: Python :: 3.6
Requires-Dist: modgrammar
